MANIFEST.in
README.md
dev_requirements.txt
setup.cfg
setup.py
versioneer.py
csirtg_network/__init__.py
csirtg_network/_version.py
csirtg_network/fqdn.py
csirtg_network/interfaces.py
csirtg_network.egg-info/PKG-INFO
csirtg_network.egg-info/SOURCES.txt
csirtg_network.egg-info/dependency_links.txt
csirtg_network.egg-info/requires.txt
csirtg_network.egg-info/top_level.txt
test/__init__.py
test/test_fqdn.py
test/test_interfaces.py