Metadata-Version: 1.1
Name: csirtg-network
Version: 0.0a1
Summary: CSIRTG Indicator Framework
Home-page: https://github.com/csirtgadgets/csirtg-network-py
Author: Wes Young
Author-email: wes@csirtgadgets.com
License: MPL2
Keywords: network
Platform: UNKNOWN
Classifier: Topic :: System :: Networking
Classifier: Environment :: Other Environment
Classifier: Intended Audience :: Developers
Classifier: Programming Language :: Python
